Metadata-Version: 1.0
Name: stats-distributions-utils
Version: 0.1
Summary: Gaussian distributions
Home-page: UNKNOWN
Author: Sebastian Birk
Author-email: sebastian.birk@outlook.com
License: UNKNOWN
Platform: UNKNOWN
